b3integration_mig24/__init__.py
b3integration_mig24/admin.py
b3integration_mig24/apps.py
b3integration_mig24/constants.py
b3integration_mig24/models.py
b3integration_mig24/seeds.py
b3integration_mig24/tests.py
b3integration_mig24/management/__init__.py
b3integration_mig24/management/commands/__init__.py
b3integration_mig24/management/commands/get_raw_mchd.py
b3integration_mig24/migrations/0001_initial.py
b3integration_mig24/migrations/0002_add_fields_to_settings.py
b3integration_mig24/migrations/__init__.py
big3_integration_mig24-0.1.dev9.dist-info/METADATA
big3_integration_mig24-0.1.dev9.dist-info/WHEEL
big3_integration_mig24-0.1.dev9.dist-info/licenses/LICENSE
big3_integration_mig24-0.1.dev9.dist-info/RECORD
