Metadata-Version: 2.3
Name: big3_integration_mig24
Version: 0.1.dev9
Summary: Интеграция с МИГ24, для проектов на базе платформы конструктора.
Author-email: BIG3 <info@big3.ru>, Нестеренко Михаил Васильевич <m.nesterenko@big3.ru>
License-File: LICENSE
Classifier: Operating System :: OS Independent
Classifier: Programming Language :: Python :: 3.10
Requires-Python: >=3.10.0
